{"www.zhihu.com":{"/":{"KLBRSID":{"key":"KLBRSID","value":"2177cbf908056c6654e972f5ddc96dc2|1580273087|1580272702","domain":"www.zhihu.com","path":"/","hostOnly":true,"creation":"2020-01-29T04:38:22.986Z","lastAccessed":"2020-01-29T04:44:48.344Z"}}},"zhihu.com":{"/":{"_xsrf":{"key":"_xsrf","value":"Ak8xJs8z0PEcCWg4JMI5XSVYHuwkqFR5","expires":"2022-07-17T04:38:57.000Z","domain":"zhihu.com","path":"/","hostOnly":false,"creation":"2020-01-29T04:38:47.101Z","lastAccessed":"2020-01-29T04:44:47.838Z"},"_zap":{"key":"_zap","value":"1dbdd2d4-3ef3-4a73-a302-e984dea89ce0","expires":"2022-01-28T04:38:47.000Z","domain":"zhihu.com","path":"/","hostOnly":false,"creation":"2020-01-29T04:38:47.653Z","lastAccessed":"2020-01-29T04:44:47.838Z"},"capsion_ticket":{"key":"capsion_ticket","value":"\"2|1:0|10:1580272732|14:capsion_ticket|44:OWY5NTg5ODc1N2I2NDEwYjgxNjBjMmNlYzVmZjEwMWY=|791ba5ba25d70ab6c82f00c8cd8283c201e7921483919e65d48365fb64b9f410\"","expires":"2020-02-28T04:38:52.000Z","domain":"zhihu.com","path":"/","httpOnly":true,"hostOnly":false,"creation":"2020-01-29T04:38:52.781Z","lastAccessed":"2020-01-29T04:44:47.838Z"},"z_c0":{"key":"z_c0","value":"\"2|1:0|10:1580272743|4:z_c0|80:MS4xRGM5UkF3QUFBQUFtQUFBQVlBSlZUV2RhSGw5MTFEZVFwWTM0VGNrTUV0d1NEeU1YRGtURmN3PT0=|553c497f137b0a3610f92ae38fbfa75a5a8580f1de5081cec20621ee2b07383c\"","expires":"2020-07-27T04:39:03.000Z","domain":"zhihu.com","path":"/","secure":true,"httpOnly":true,"hostOnly":false,"creation":"2020-01-29T04:39:04.221Z","lastAccessed":"2020-01-29T04:44:47.838Z"}}}}