{"www.zhihu.com":{"/":{"KLBRSID":{"key":"KLBRSID","value":"5430ad6ccb1a51f38ac194049bce5dfe|1580301125|1580300953","domain":"www.zhihu.com","path":"/","hostOnly":true,"creation":"2020-01-29T06:11:31.884Z","lastAccessed":"2020-01-29T12:32:05.797Z"}}},"zhihu.com":{"/":{"_xsrf":{"key":"_xsrf","value":"jhyilY08vCvdpO1m3CfpDF45s4XhKFOi","expires":"2022-07-17T07:13:24.000Z","domain":"zhihu.com","path":"/","hostOnly":false,"creation":"2020-01-29T07:13:24.632Z","lastAccessed":"2020-01-29T12:32:05.167Z"},"_zap":{"key":"_zap","value":"ca662a01-72f6-4e48-b982-443618c8366a","expires":"2022-01-28T07:13:24.000Z","domain":"zhihu.com","path":"/","hostOnly":false,"creation":"2020-01-29T07:13:24.879Z","lastAccessed":"2020-01-29T12:32:05.167Z"},"capsion_ticket":{"key":"capsion_ticket","value":"\"2|1:0|10:1580301068|14:capsion_ticket|44:NjcxNGY1YzdkNzE1NGFjMTk5NjIzOTAxZmJkNTJiOTQ=|240b40eaa4983b9c4e1417f1885c0420214efb8634d1da261c8b87d4cdda18ae\"","expires":"2020-02-28T12:31:08.000Z","domain":"zhihu.com","path":"/","httpOnly":true,"hostOnly":false,"creation":"2020-01-29T07:13:27.231Z","lastAccessed":"2020-01-29T12:32:05.167Z"}}}}